README.md
setup.cfg
setup.py
tests/__init__.py
tests/test_cli.py
tests/test_twselib.py
twsecli/__init__.py
twsecli/cli.py
twsecli/lib.py
twsecli.egg-info/PKG-INFO
twsecli.egg-info/SOURCES.txt
twsecli.egg-info/dependency_links.txt
twsecli.egg-info/entry_points.txt
twsecli.egg-info/requires.txt
twsecli.egg-info/top_level.txt