Metadata-Version: 2.1
Name: twsecli
Version: 0.7.0
Summary: TWSE unofficial command-line interface
Home-page: https://github.com/hansliu/twsecli
Author: Hans Liu
Author-email: hansliu.tw@gmail.com
License: UNKNOWN
Keywords: twse
Platform: UNKNOWN
Classifier: License :: OSI Approved :: MIT License
Classifier: Programming Language :: Python :: 3
Requires-Python: >=3
